pysymvea/__init__.py
pysymvea/cli.py
pysymvea/client.py
pysymvea-0.1.0.dist-info/licenses/LICENSE
pysymvea-0.1.0.dist-info/METADATA
pysymvea-0.1.0.dist-info/WHEEL
pysymvea-0.1.0.dist-info/entry_points.txt
pysymvea-0.1.0.dist-info/top_level.txt
pysymvea-0.1.0.dist-info/RECORD
